dm_robotics/transformations/__init__.py
dm_robotics/transformations/_transformations.py
dm_robotics/transformations/_transformations_quat.py
dm_robotics/transformations/_types.py
dm_robotics/transformations/transformations.py
dm_robotics/transformations/transformations_test.py
dm_robotics/transformations/jax_transformations/transformations.py
dm_robotics/transformations/jax_transformations/transformations_test.py
dm_robotics_transformations-0.10.0.dist-info/METADATA
dm_robotics_transformations-0.10.0.dist-info/WHEEL
dm_robotics_transformations-0.10.0.dist-info/top_level.txt
dm_robotics_transformations-0.10.0.dist-info/zip-safe
dm_robotics_transformations-0.10.0.dist-info/RECORD
