Metadata-Version: 2.4
Name: dm_robotics-transformations
Version: 0.10.0
Summary: A library for Rigid Body Transformations
Home-page: https://github.com/deepmind/dm_robotics/tree/main/py/transformations
Author: DeepMind
License: Apache 2.0
Classifier: Development Status :: 5 - Production/Stable
Classifier: Programming Language :: Python :: 3
Classifier: License :: OSI Approved :: Apache Software License
Classifier: Operating System :: OS Independent
Classifier: Topic :: Software Development :: Libraries
Classifier: Topic :: Scientific/Engineering
Classifier: Topic :: Scientific/Engineering :: Mathematics
Requires-Dist: pip>=20.0.2
Requires-Dist: absl-py>=0.9.0
Requires-Dist: numpy<3.0,>=2.0
Requires-Dist: jax>=0.4.13
Provides-Extra: quaternion
Requires-Dist: numpy-quaternion==v2024.0.10; extra == "quaternion"
Dynamic: author
Dynamic: classifier
Dynamic: description
Dynamic: description-content-type
Dynamic: home-page
Dynamic: license
Dynamic: provides-extra
Dynamic: requires-dist
Dynamic: summary
